LICENSE
MANIFEST.in
README.rst
requirements.txt
setup.py
cleanfreak/__init__.py
cleanfreak/app.py
cleanfreak/checker.py
cleanfreak/config.py
cleanfreak/messages.py
cleanfreak/shout.py
cleanfreak/utils.py
cleanfreak.egg-info/PKG-INFO
cleanfreak.egg-info/SOURCES.txt
cleanfreak.egg-info/dependency_links.txt
cleanfreak.egg-info/top_level.txt
cleanfreak/conf/config.yml
cleanfreak/conf/mayacheckers.py
cleanfreak/ui/__init__.py
cleanfreak/ui/cleanfreak.png
cleanfreak/ui/mayaui.py
cleanfreak/ui/style.css
cleanfreak/ui/ui.py