Metadata-Version: 1.1
Name: cleanfreak
Version: 0.1.5
Summary: Sanity checks and grades for CG production.
Home-page: http://github.com/danbradham/cleanfreak
Author: Dan Bradham
Author-email: danielbradham@gmail.com
License: MIT
Platform: UNKNOWN
Classifier: Development Status :: 3 - Alpha
Classifier: Intended Audience :: Developers
Classifier: License :: OSI Approved :: MIT License
Classifier: Natural Language :: English
Classifier: Operating System :: OS Independent
Classifier: Programming Language :: Python
Classifier: Programming Language :: Python :: 2
Classifier: Programming Language :: Python :: 3
Classifier: Topic :: Software Development :: Libraries :: Python Modules
